[ { "domain":"hugo.utermux.dev","subject":"CN=*.utermux.dev","start":"Jun 1 01:54:45 2024 GMT","expire":"Jul 1 01:54:44 2025 GMT","issuer":"C=US; O=NYA LABS LLC; CN=Nya Labs CA","status":"即将失效","statuscolor":"warning","check":"2025-02-27 00:07:39","remain":"124"},{"domain":"blog.utermux.dev","subject":"CN=*.utermux.dev","start":"Jun 1 01:54:45 2024 GMT","expire":"Jul 1 01:54:44 2025 GMT","issuer":"C=US; O=NYA LABS LLC; CN=Nya Labs CA","status":"即将失效","statuscolor":"warning","check":"2025-02-27 00:07:40","remain":"124"},{"domain":"mirrors.utermux.dev","subject":"CN=*.utermux.dev","start":"Jun 1 01:54:45 2024 GMT","expire":"Jul 1 01:54:44 2025 GMT","issuer":"C=US; O=NYA LABS LLC; CN=Nya Labs CA","status":"即将失效","statuscolor":"warning","check":"2025-02-27 00:07:41","remain":"124"},{"domain":"www.utermux.dev","subject":"CN=*.utermux.dev","start":"Jun 1 01:54:45 2024 GMT","expire":"Jul 1 01:54:44 2025 GMT","issuer":"C=US; O=NYA LABS LLC; CN=Nya Labs CA","status":"即将失效","statuscolor":"warning","check":"2025-02-27 00:07:42","remain":"124"},{"domain":"alist.utermux.dev","subject":"CN=*.utermux.dev","start":"Jun 1 01:54:45 2024 GMT","expire":"Jul 1 01:54:44 2025 GMT","issuer":"C=US; O=NYA LABS LLC; CN=Nya Labs CA","status":"即将失效","statuscolor":"warning","check":"2025-02-27 00:07:42","remain":"124"},{"domain":"utermux.dev","subject":"CN=*.utermux.dev","start":"Jun 1 01:54:45 2024 GMT","expire":"Jul 1 01:54:44 2025 GMT","issuer":"C=US; O=NYA LABS LLC; CN=Nya Labs CA","status":"即将失效","statuscolor":"warning","check":"2025-02-27 00:07:43","remain":"124" } ]
