[ { "domain":"hugo.utermux.dev","subject":"CN=*.utermux.dev","start":"Jun 1 01:54:45 2024 GMT","expire":"Jul 1 01:54:44 2025 GMT","issuer":"C=US; O=NYA LABS LLC; CN=Nya Labs CA","status":"即将失效","statuscolor":"warning","check":"2025-03-02 00:06:11","remain":"121"},{"domain":"blog.utermux.dev","subject":"CN=*.utermux.dev","start":"Jun 1 01:54:45 2024 GMT","expire":"Jul 1 01:54:44 2025 GMT","issuer":"C=US; O=NYA LABS LLC; CN=Nya Labs CA","status":"即将失效","statuscolor":"warning","check":"2025-03-02 00:06:15","remain":"121"},{"domain":"mirrors.utermux.dev","subject":"CN=*.utermux.dev","start":"Jun 1 01:54:45 2024 GMT","expire":"Jul 1 01:54:44 2025 GMT","issuer":"C=US; O=NYA LABS LLC; CN=Nya Labs CA","status":"即将失效","statuscolor":"warning","check":"2025-03-02 00:06:15","remain":"121"},{"domain":"www.utermux.dev","subject":"CN=*.utermux.dev","start":"Jun 1 01:54:45 2024 GMT","expire":"Jul 1 01:54:44 2025 GMT","issuer":"C=US; O=NYA LABS LLC; CN=Nya Labs CA","status":"即将失效","statuscolor":"warning","check":"2025-03-02 00:06:17","remain":"121"},{"domain":"alist.utermux.dev","subject":"CN=*.utermux.dev","start":"Jun 1 01:54:45 2024 GMT","expire":"Jul 1 01:54:44 2025 GMT","issuer":"C=US; O=NYA LABS LLC; CN=Nya Labs CA","status":"即将失效","statuscolor":"warning","check":"2025-03-02 00:06:18","remain":"121"},{"domain":"utermux.dev","subject":"CN=*.utermux.dev","start":"Jun 1 01:54:45 2024 GMT","expire":"Jul 1 01:54:44 2025 GMT","issuer":"C=US; O=NYA LABS LLC; CN=Nya Labs CA","status":"即将失效","statuscolor":"warning","check":"2025-03-02 00:06:20","remain":"121" } ]
